audible/__init__.py
audible/_logging.py
audible/_types.py
audible/activation_bytes.py
audible/aescipher.py
audible/auth.py
audible/client.py
audible/exceptions.py
audible/localization.py
audible/login.py
audible/metadata.py
audible/py.typed
audible/register.py
audible/utils.py
audible-0.10.0.dist-info/LICENSE
audible-0.10.0.dist-info/METADATA
audible-0.10.0.dist-info/WHEEL
audible-0.10.0.dist-info/RECORD
