Metadata-Version: 2.1
Name: audible
Version: 0.10.0
Summary: A(Sync) Interface for internal Audible API written in pure Python.
Home-page: https://github.com/mkb79/Audible
License: AGPL-3.0-only
Keywords: Audible,API,async
Author: mkb79
Author-email: mkb79@hackitall.de
Requires-Python: >=3.10,<3.13
Classifier: Development Status :: 4 - Beta
Classifier: Intended Audience :: Developers
Classifier: License :: OSI Approved :: GNU Affero General Public License v3
Classifier: Programming Language :: Python :: 3
Classifier: Programming Language :: Python :: 3.10
Classifier: Programming Language :: Python :: 3.11
Classifier: Programming Language :: Python :: 3.12
Requires-Dist: Pillow (>=9.4.0)
Requires-Dist: beautifulsoup4 (>=4.11.2)
Requires-Dist: httpx (>=0.23.3)
Requires-Dist: pbkdf2 (>=1.3)
Requires-Dist: pyaes (>=1.6.1)
Requires-Dist: rsa (>=4.9)
Project-URL: Changelog, https://github.com/mkb79/Audible/releases
Project-URL: Documentation, https://audible.readthedocs.io
Project-URL: Repository, https://github.com/mkb79/Audible
